calkulate/__init__.py
calkulate/classes.py
calkulate/constants.py
calkulate/convert.py
calkulate/core.py
calkulate/dataset.py
calkulate/default.py
calkulate/density.py
calkulate/files.py
calkulate/interface.py
calkulate/loss.py
calkulate/meta.py
calkulate/settings.py
calkulate/simulate.py
calkulate/plot/__init__.py
calkulate/plot/misc.py
calkulate/plot/titration.py
calkulate/read/__init__.py
calkulate/read/metadata.py
calkulate/read/titrations.py
calkulate-23.7.0.dist-info/licenses/LICENSE
calkulate-23.7.0.dist-info/METADATA
calkulate-23.7.0.dist-info/WHEEL
calkulate-23.7.0.dist-info/top_level.txt
calkulate-23.7.0.dist-info/RECORD
